README.md
setup.py
ks_encrypt/__init__.py
ks_encrypt/ks_encrypt_cn.py
ks_encrypt/ks_encrypt_kb.py
ks_encrypt/ks_encrypt_s.py
ksen.egg-info/PKG-INFO
ksen.egg-info/SOURCES.txt
ksen.egg-info/dependency_links.txt
ksen.egg-info/top_level.txt