Metadata-Version: 2.1
Name: ksen
Version: 1.2-1
Summary: Caesar encryption
Home-page: UNKNOWN
Author: qinyuyao
Author-email: 3255458795@qq.com
License: UNKNOWN
Platform: UNKNOWN
Classifier: Programming Language :: Python :: 3
Classifier: License :: OSI Approved :: MIT License
Classifier: Operating System :: OS Independent
